setup.cfg
setup.py
u_cli.egg-info/PKG-INFO
u_cli.egg-info/SOURCES.txt
u_cli.egg-info/dependency_links.txt
u_cli.egg-info/entry_points.txt
u_cli.egg-info/requires.txt
u_cli.egg-info/top_level.txt
u_cli.egg-info/zip-safe
ucli/UCliMain.py
ucli/UCloudApiClient.py
ucli/UCloudApiConfig.py
ucli/__init__.py