Metadata-Version: 1.0
Name: u-cli
Version: 0.1.8
Summary: A UCloud Command Line tool base on UCloud api
Home-page: https://github.com/hsiun/ucli
Author: hsiun
Author-email: growdane@gmail.com
License: MIT
Keywords: python ucloud api sdk uhost ufile ucli command line
Platform: UNKNOWN
